{"name": "Dungeons-Route - vw-cthun", "data": {"Spymasters_Web": {"639": 1624162, "626": 1611222, "619": 1604858, "606": 1593890}, "AraKara_Sacbrood": {"639": 1612829, "626": 1601852, "619": 1596261, "606": 1586801, "593": 1578814}, "Gale_of_Shadows": {"639": 1604347, "626": 1594363, "619": 1589462, "606": 1580852}, "Unbound_Changeling_Haste": {"639": 1598108, "626": 1588580, "619": 1583764, "606": 1575630, "593": 1568308}, "Unbound_Changeling_All": {"639": 1597143, "626": 1587412, "619": 1582850, "606": 1574483, "593": 1567251}, "Empowering_Crystal_of_Anubikkaj": {"639": 1596005, "626": 1586600, "619": 1581687, "606": 1573916, "593": 1566754}, "Aberrant_Spellforge": {"639": 1595639, "626": 1585984, "619": 1581597, "606": 1573815}, "Unbound_Changeling_Mastery": {"639": 1594818, "626": 1585200, "619": 1580711, "606": 1572545, "593": 1565777}, "Ovinaxs_Mercurial_Egg": {"639": 1594255, "626": 1584100, "619": 1579243, "606": 1570656}, "Candle_Confidant": {"626": 1594239, "619": 1589840, "606": 1582873}, "Unbound_Changeling_Crit": {"639": 1593728, "626": 1584616, "619": 1579763, "606": 1571570, "593": 1564605}, "Vigilance_Charm": {"626": 1591070}, "Forged_Gladiators_Insignia_of_Alacrity": {"626": 1589292}, "Shadowbinding_Ritual_Knife": {"626": 1588986, "619": 1583873, "606": 1574957}, "Satchel_of_Misbegotten_Minions": {"639": 1587720, "626": 1578494, "619": 1574264, "606": 1567314, "593": 1561614}, "Quickwick_Candlestick": {"626": 1587054, "619": 1582380, "606": 1574471}, "Pandoras_Plea": {"619": 1586415}, "Horn_of_Declaration": {"626": 1584732, "619": 1579978, "606": 1572364}, "Mindtap_Talisman": {"626": 1584279}, "Harvesters_Edict_20%": {"639": 1584187, "626": 1575667, "619": 1571176, "606": 1564497, "593": 1557924}, "Elemental_Focus_Stone": {"619": 1583385}, "Eye_of_the_Broodmother": {"619": 1582609}, "Scale_of_Fates": {"619": 1582478}, "Concoction_Kiss_of_Death": {"626": 1582446, "619": 1577594, "606": 1569882}, "Hadals_Nautilus": {"639": 1582444, "626": 1573787, "619": 1570040, "606": 1563028}, "Harvesters_Edict_5%": {"639": 1581586, "626": 1572947, "619": 1568838, "606": 1562241, "593": 1555958}, "Unstable_Power_Suit_Core": {"626": 1581540, "619": 1576911, "606": 1569046}, "Treacherous_Transmitter": {"639": 1581229, "626": 1574066, "619": 1570428, "606": 1564192}, "Hibernation_Crystal": {"626": 1580516}, "Necromantic_Focus": {"619": 1580265}, "Flare_of_the_Heavens": {"619": 1579553}, "Energy_Siphon": {"619": 1579348}, "Everburning_Lantern": {"626": 1578977, "619": 1575311, "606": 1568156}, "Kaheti_Shadeweavers_Emblem": {"626": 1578302, "619": 1574114, "606": 1567230}, "Mereldars_Toll": {"639": 1577275, "626": 1568778, "619": 1565075, "606": 1558122, "593": 1552354}, "Mad_Queens_Mandate": {"639": 1577155, "626": 1568654, "619": 1564529, "606": 1557132}, "The_Skull_of_Guldan": {"619": 1576726}, "Imperfect_Ascendancy_Serum": {"626": 1573718, "619": 1569627, "606": 1561823}, "Forged_Gladiators_Badge_of_Ferocity": {"626": 1573609}, "Living_Flame": {"619": 1570485}, "Cirral_Concoctory": {"639": 1570264, "626": 1562252, "619": 1558700, "606": 1552043, "593": 1546404}, "Carved_Blazikon_Wax": {"593": 1565058}, "Signet_of_the_Priory": {"593": 1564244}, "High_Speakers_Accretion": {"639": 1563625, "626": 1557380, "619": 1554714, "606": 1549477, "593": 1544576}, "Entropic_Skardyn_Core": {"593": 1563524}, "Fungal_Friend_Flute": {"626": 1562480, "619": 1558388, "606": 1552486}, "Nizreks_Holographic_Manipulator": {"626": 1562257, "619": 1558587, "606": 1552291}, "Sigil_of_Algari_Concordance": {"593": 1560548}, "Variable_Pulse_Lightning_Capacitor": {"619": 1558489}, "Remnant_of_Darkness": {"593": 1554108}, "Bursting_Lightshard": {"593": 1546509}, "Synergistic_Brewterializer": {"593": 1546405}, "Ramsteins_Lightning_Bolts": {"626": 1542173}, "Cannonball_Runner": {"626": 1523120}, "Vanquished_Clutches_of_Yogg_Saron": {"619": 1522487}, "Doperels_Calling_Rune": {"626": 1501797}, "Burst_of_Knowledge": {"626": 1501722}, "Base": {"DPS": 1501617}}, "ids": {"Spymasters_Web": 220202, "AraKara_Sacbrood": 219314, "Gale_of_Shadows": 133304, "Unbound_Changeling_Haste": 178708, "Unbound_Changeling_All": 178708, "Empowering_Crystal_of_Anubikkaj": 219312, "Aberrant_Spellforge": 212451, "Unbound_Changeling_Mastery": 178708, "Ovinaxs_Mercurial_Egg": 220305, "Candle_Confidant": 225648, "Unbound_Changeling_Crit": 178708, "Vigilance_Charm": 18370, "Forged_Gladiators_Insignia_of_Alacrity": 218714, "Shadowbinding_Ritual_Knife": 215178, "Satchel_of_Misbegotten_Minions": 178772, "Quickwick_Candlestick": 225649, "Pandoras_Plea": 156207, "Horn_of_Declaration": 217041, "Mindtap_Talisman": 18371, "Harvesters_Edict_20%": 219317, "Elemental_Focus_Stone": 156288, "Eye_of_the_Broodmother": 156036, "Scale_of_Fates": 156187, "Concoction_Kiss_of_Death": 215174, "Hadals_Nautilus": 159622, "Harvesters_Edict_5%": 219317, "Unstable_Power_Suit_Core": 225668, "Treacherous_Transmitter": 221023, "Hibernation_Crystal": 150388, "Necromantic_Focus": 171644, "Flare_of_the_Heavens": 156230, "Energy_Siphon": 156021, "Everburning_Lantern": 215169, "Kaheti_Shadeweavers_Emblem": 225651, "Mereldars_Toll": 219313, "Mad_Queens_Mandate": 212454, "The_Skull_of_Guldan": 150522, "Imperfect_Ascendancy_Serum": 225654, "Forged_Gladiators_Badge_of_Ferocity": 218713, "Living_Flame": 155947, "Cirral_Concoctory": 219321, "Carved_Blazikon_Wax": 219305, "Signet_of_the_Priory": 219308, "High_Speakers_Accretion": 219303, "Entropic_Skardyn_Core": 219296, "Fungal_Friend_Flute": 215171, "Nizreks_Holographic_Manipulator": 225970, "Sigil_of_Algari_Concordance": 219295, "Variable_Pulse_Lightning_Capacitor": 171640, "Remnant_of_Darkness": 219307, "Bursting_Lightshard": 219310, "Synergistic_Brewterializer": 219299, "Ramsteins_Lightning_Bolts": 13515, "Cannonball_Runner": 13382, "Vanquished_Clutches_of_Yogg_Saron": 156458, "Doperels_Calling_Rune": 231476, "Burst_of_Knowledge": 231424}, "simulated_steps": [639, 629, 626, 619, 606, 593], "sorted_data_keys": ["Spymasters_Web", "AraKara_Sacbrood", "Gale_of_Shadows", "Unbound_Changeling_Haste", "Unbound_Changeling_All", "Empowering_Crystal_of_Anubikkaj", "Aberrant_Spellforge", "Unbound_Changeling_Mastery", "Ovinaxs_Mercurial_Egg", "Candle_Confidant", "Unbound_Changeling_Crit", "Vigilance_Charm", "Forged_Gladiators_Insignia_of_Alacrity", "Shadowbinding_Ritual_Knife", "Satchel_of_Misbegotten_Minions", "Quickwick_Candlestick", "Pandoras_Plea", "Horn_of_Declaration", "Mindtap_Talisman", "Harvesters_Edict_20%", "Elemental_Focus_Stone", "Eye_of_the_Broodmother", "Scale_of_Fates", "Concoction_Kiss_of_Death", "Hadals_Nautilus", "Harvesters_Edict_5%", "Unstable_Power_Suit_Core", "Treacherous_Transmitter", "Hibernation_Crystal", "Necromantic_Focus", "Flare_of_the_Heavens", "Energy_Siphon", "Everburning_Lantern", "Kaheti_Shadeweavers_Emblem", "Mereldars_Toll", "Mad_Queens_Mandate", "The_Skull_of_Guldan", "Imperfect_Ascendancy_Serum", "Forged_Gladiators_Badge_of_Ferocity", "Living_Flame", "Cirral_Concoctory", "Carved_Blazikon_Wax", "Signet_of_the_Priory", "High_Speakers_Accretion", "Entropic_Skardyn_Core", "Fungal_Friend_Flute", "Nizreks_Holographic_Manipulator", "Sigil_of_Algari_Concordance", "Variable_Pulse_Lightning_Capacitor", "Remnant_of_Darkness", "Bursting_Lightshard", "Synergistic_Brewterializer", "Ramsteins_Lightning_Bolts", "Cannonball_Runner", "Vanquished_Clutches_of_Yogg_Saron", "Doperels_Calling_Rune", "Burst_of_Knowledge"], "last_updated": "2024-10-04"}