{"name": "2T - ar-vf-yogg-cthun-me", "data": {"Astral_Antenna": {"723": 7337901, "710": 7275831, "704": 7253083, "691": 7196514}, "Arazs_Ritual_Forge": {"723": 7304822, "710": 7241491, "704": 7213663, "691": 7156947}, "Signet_of_the_Priory": {"723": 7279114, "710": 7221560}, "Diamantine_Voidcore_Prepull_NoMana_Weapon": {"723": 7276269, "710": 7217548, "704": 7192885, "691": 7146132}, "Azhiccaran_Parapodia": {"723": 7269007, "710": 7209686}, "Diamantine_Voidcore_Weapon": {"723": 7254597, "710": 7201647, "704": 7176816, "691": 7129007}, "Incorporeal_Essence_Gorger_NonEthereal": {"710": 7247915, "704": 7218747}, "Empowering_Crystal_of_Anubikkaj": {"723": 7240923, "710": 7183803}, "AraKara_Sacbrood": {"723": 7235645, "710": 7178960}, "Lily_of_the_Eternal_Weave": {"723": 7233915, "710": 7178944}, "Soleahs_Secret_Technique_Crit": {"723": 7232520, "710": 7173116}, "Soleahs_Secret_Technique_Haste": {"723": 7230584, "710": 7171682}, "Gigazaps_Zap_Cap": {"723": 7230359, "710": 7156502}, "Soleahs_Secret_Technique_Versatility": {"723": 7229261, "710": 7171957}, "Living_Flame": {"704": 7225753}, "Energy_Siphon": {"704": 7223161}, "Incorporeal_Essence_Gorger_Ethereal": {"710": 7221588, "704": 7196675}, "Soleahs_Secret_Technique_Mastery": {"723": 7219090, "710": 7161956}, "Mugs_Moxie_Jug": {"684": 7190837}, "Diamantine_Voidcore_Prepull_NoMana": {"723": 7183139, "710": 7129218, "704": 7103450, "691": 7055512}, "Naazindhris_Mystic_Lash": {"723": 7175426, "710": 7109681, "704": 7081921, "691": 7029707}, "Scale_of_Fates": {"704": 7174167}, "Eye_of_the_Broodmother": {"704": 7166841}, "Diamantine_Voidcore": {"723": 7162493, "710": 7108470, "704": 7084589, "691": 7040611}, "Harvesters_Edict_20%": {"723": 7156728, "710": 7099892}, "Astral_Gladiators_Badge_of_Ferocity": {"704": 7154950}, "Pandoras_Plea": {"704": 7154190}, "Flare_of_the_Heavens": {"704": 7148808}, "Elemental_Focus_Stone": {"704": 7145867}, "Astral_Gladiators_Insignia_of_Alacrity": {"704": 7137908}, "Voidtouched_Fragment": {"710": 7136992, "704": 7114267}, "The_Skull_of_Guldan": {"704": 7136328}, "Mereldars_Toll": {"723": 7126813, "710": 7070090}, "Essence_Hunters_Eyeglass": {"710": 7126223, "704": 7103259}, "Sunblood_Amethyst": {"723": 7125556, "710": 7081946}, "Soulbreakers_Sigil": {"710": 7122976, "704": 7093175}, "Automatic_Footbomb_Dispenser": {"710": 7107294, "704": 7080635}, "Hibernation_Crystal": {"691": 7102416}, "House_of_Cards": {"684": 7088861}, "Bursting_Lightshard": {"723": 7073427, "710": 7025092}, "Eye_of_Kezan": {"684": 7060720}, "Perfidious_Projector": {"723": 7037275, "710": 7002093, "704": 6987890, "691": 6958419}, "Miniscule_Mailemental_in_an_Envelope": {"723": 7016151, "710": 6984863}, "Variable_Pulse_Lightning_Capacitor": {"704": 7003626}, "Screams_of_a_Forgotten_Sky": {"723": 6999774, "710": 6968342, "704": 6957347, "691": 6930686}, "Chaotic_Nethergate": {"710": 6933010, "704": 6922759}, "Vanquished_Clutches_of_Yogg_Saron": {"704": 6799769}, "Base": {"DPS": 6645686}}, "ids": {"Astral_Antenna": 242395, "Arazs_Ritual_Forge": 242402, "Signet_of_the_Priory": 219308, "Diamantine_Voidcore_Prepull_NoMana_Weapon": 242392, "Azhiccaran_Parapodia": 242497, "Diamantine_Voidcore_Weapon": 242392, "Incorporeal_Essence_Gorger_NonEthereal": 246945, "Empowering_Crystal_of_Anubikkaj": 219312, "AraKara_Sacbrood": 219314, "Lily_of_the_Eternal_Weave": 242494, "Soleahs_Secret_Technique_Crit": 190958, "Soleahs_Secret_Technique_Haste": 190958, "Gigazaps_Zap_Cap": 232545, "Soleahs_Secret_Technique_Versatility": 190958, "Living_Flame": 155947, "Energy_Siphon": 156021, "Incorporeal_Essence_Gorger_Ethereal": 246945, "Soleahs_Secret_Technique_Mastery": 190958, "Mugs_Moxie_Jug": 230192, "Diamantine_Voidcore_Prepull_NoMana": 242392, "Naazindhris_Mystic_Lash": 242398, "Scale_of_Fates": 156187, "Eye_of_the_Broodmother": 156036, "Diamantine_Voidcore": 242392, "Harvesters_Edict_20%": 219317, "Astral_Gladiators_Badge_of_Ferocity": 230638, "Pandoras_Plea": 156207, "Flare_of_the_Heavens": 156230, "Elemental_Focus_Stone": 156288, "Astral_Gladiators_Insignia_of_Alacrity": 230639, "Voidtouched_Fragment": 238386, "The_Skull_of_Guldan": 150522, "Mereldars_Toll": 219313, "Essence_Hunters_Eyeglass": 246939, "Sunblood_Amethyst": 178826, "Soulbreakers_Sigil": 238390, "Automatic_Footbomb_Dispenser": 242867, "Hibernation_Crystal": 150388, "House_of_Cards": 230027, "Bursting_Lightshard": 219310, "Eye_of_Kezan": 230198, "Perfidious_Projector": 242403, "Miniscule_Mailemental_in_an_Envelope": 185846, "Variable_Pulse_Lightning_Capacitor": 171640, "Screams_of_a_Forgotten_Sky": 242399, "Chaotic_Nethergate": 246825, "Vanquished_Clutches_of_Yogg_Saron": 156458}, "simulated_steps": [723, 710, 704, 691, 684], "sorted_data_keys": ["Astral_Antenna", "Arazs_Ritual_Forge", "Signet_of_the_Priory", "Diamantine_Voidcore_Prepull_NoMana_Weapon", "Azhiccaran_Parapodia", "Diamantine_Voidcore_Weapon", "Incorporeal_Essence_Gorger_NonEthereal", "Empowering_Crystal_of_Anubikkaj", "AraKara_Sacbrood", "Lily_of_the_Eternal_Weave", "Soleahs_Secret_Technique_Crit", "Soleahs_Secret_Technique_Haste", "Gigazaps_Zap_Cap", "Soleahs_Secret_Technique_Versatility", "Living_Flame", "Energy_Siphon", "Incorporeal_Essence_Gorger_Ethereal", "Soleahs_Secret_Technique_Mastery", "Mugs_Moxie_Jug", "Diamantine_Voidcore_Prepull_NoMana", "Naazindhris_Mystic_Lash", "Scale_of_Fates", "Eye_of_the_Broodmother", "Diamantine_Voidcore", "Harvesters_Edict_20%", "Astral_Gladiators_Badge_of_Ferocity", "Pandoras_Plea", "Flare_of_the_Heavens", "Elemental_Focus_Stone", "Astral_Gladiators_Insignia_of_Alacrity", "Voidtouched_Fragment", "The_Skull_of_Guldan", "Mereldars_Toll", "Essence_Hunters_Eyeglass", "Sunblood_Amethyst", "Soulbreakers_Sigil", "Automatic_Footbomb_Dispenser", "Hibernation_Crystal", "House_of_Cards", "Bursting_Lightshard", "Eye_of_Kezan", "Perfidious_Projector", "Miniscule_Mailemental_in_an_Envelope", "Variable_Pulse_Lightning_Capacitor", "Screams_of_a_Forgotten_Sky", "Chaotic_Nethergate", "Vanquished_Clutches_of_Yogg_Saron"], "last_updated": "2025-08-21"}