{"name": "Composite - vw-da-cthun", "data": {"Astral_Antenna": {"723": 4736620, "710": 4696525, "704": 4679510, "691": 4643683}, "Arazs_Ritual_Forge": {"723": 4733728, "710": 4690712, "704": 4671184, "691": 4633620}, "Diamantine_Voidcore_Prepull_NoMana_Weapon": {"723": 4729704, "710": 4694587, "704": 4678167, "691": 4646290}, "Diamantine_Voidcore_Weapon": {"723": 4722083, "710": 4685750, "704": 4670988, "691": 4638894}, "Lily_of_the_Eternal_Weave": {"723": 4716696, "710": 4677866}, "Signet_of_the_Priory": {"723": 4710016, "710": 4670131}, "Azhiccaran_Parapodia": {"723": 4695257, "710": 4654549}, "Incorporeal_Essence_Gorger": {"710": 4687098, "704": 4670936}, "Living_Flame": {"704": 4685295}, "Empowering_Crystal_of_Anubikkaj": {"723": 4681148, "710": 4643888}, "Diamantine_Voidcore_Prepull_NoMana": {"723": 4680240, "710": 4642919, "704": 4628056, "691": 4596377}, "Soleahs_Secret_Technique_Mastery": {"723": 4679828, "710": 4642877}, "Soleahs_Secret_Technique_Versatility": {"723": 4678659, "710": 4640517}, "Soleahs_Secret_Technique_Crit": {"723": 4676843, "710": 4639251}, "Energy_Siphon": {"704": 4674172}, "Diamantine_Voidcore": {"723": 4673389, "710": 4636718, "704": 4621277, "691": 4589359}, "AraKara_Sacbrood": {"723": 4670019, "710": 4631630}, "Astral_Gladiators_Badge_of_Ferocity": {"704": 4665050}, "Gigazaps_Zap_Cap": {"723": 4659460, "710": 4614215}, "Soleahs_Secret_Technique_Haste": {"723": 4657554, "710": 4619142}, "Naazindhris_Mystic_Lash": {"723": 4645465, "710": 4604020, "704": 4584550, "691": 4547832}, "Eye_of_the_Broodmother": {"704": 4645098}, "Harvesters_Edict_20%": {"723": 4641948, "710": 4601780}, "Mugs_Moxie_Jug": {"684": 4638858}, "Voidtouched_Fragment": {"710": 4625791, "704": 4611589}, "Flare_of_the_Heavens": {"704": 4623794}, "Mereldars_Toll": {"723": 4621323, "710": 4584320}, "Scale_of_Fates": {"704": 4620082}, "House_of_Cards": {"684": 4614712}, "Hibernation_Crystal": {"691": 4613589}, "Soulbreakers_Sigil": {"710": 4613583, "704": 4594456}, "Essence_Hunters_Eyeglass": {"710": 4607676, "704": 4591186}, "Pandoras_Plea": {"704": 4605361}, "Elemental_Focus_Stone": {"704": 4604996}, "The_Skull_of_Guldan": {"704": 4604681}, "Sunblood_Amethyst": {"723": 4597253, "710": 4567564}, "Automatic_Footbomb_Dispenser": {"710": 4594993, "704": 4577047}, "Astral_Gladiators_Insignia_of_Alacrity": {"704": 4594115}, "Screams_of_a_Forgotten_Sky": {"723": 4586665, "710": 4559597, "704": 4546153, "691": 4521626}, "Bursting_Lightshard": {"723": 4580681, "710": 4548151}, "Eye_of_Kezan": {"684": 4579171}, "Miniscule_Mailemental_in_an_Envelope": {"723": 4559047, "710": 4531038}, "Perfidious_Projector": {"723": 4539767, "710": 4515864, "704": 4505174, "691": 4484564}, "Variable_Pulse_Lightning_Capacitor": {"704": 4532083}, "Chaotic_Nethergate": {"710": 4451689, "704": 4443924}, "Vanquished_Clutches_of_Yogg_Saron": {"704": 4384687}, "Voidglass_Kris": {"723": 4316711}, "Base": {"DPS": 4290380}}, "ids": {"Astral_Antenna": 242395, "Arazs_Ritual_Forge": 242402, "Diamantine_Voidcore_Prepull_NoMana_Weapon": 242392, "Diamantine_Voidcore_Weapon": 242392, "Lily_of_the_Eternal_Weave": 242494, "Signet_of_the_Priory": 219308, "Azhiccaran_Parapodia": 242497, "Incorporeal_Essence_Gorger": 246945, "Living_Flame": 155947, "Empowering_Crystal_of_Anubikkaj": 219312, "Diamantine_Voidcore_Prepull_NoMana": 242392, "Soleahs_Secret_Technique_Mastery": 190958, "Soleahs_Secret_Technique_Versatility": 190958, "Soleahs_Secret_Technique_Crit": 190958, "Energy_Siphon": 156021, "Diamantine_Voidcore": 242392, "AraKara_Sacbrood": 219314, "Astral_Gladiators_Badge_of_Ferocity": 230638, "Gigazaps_Zap_Cap": 232545, "Soleahs_Secret_Technique_Haste": 190958, "Naazindhris_Mystic_Lash": 242398, "Eye_of_the_Broodmother": 156036, "Harvesters_Edict_20%": 219317, "Mugs_Moxie_Jug": 230192, "Voidtouched_Fragment": 238386, "Flare_of_the_Heavens": 156230, "Mereldars_Toll": 219313, "Scale_of_Fates": 156187, "House_of_Cards": 230027, "Hibernation_Crystal": 150388, "Soulbreakers_Sigil": 238390, "Essence_Hunters_Eyeglass": 246939, "Pandoras_Plea": 156207, "Elemental_Focus_Stone": 156288, "The_Skull_of_Guldan": 150522, "Sunblood_Amethyst": 178826, "Automatic_Footbomb_Dispenser": 242867, "Astral_Gladiators_Insignia_of_Alacrity": 230639, "Screams_of_a_Forgotten_Sky": 242399, "Bursting_Lightshard": 219310, "Eye_of_Kezan": 230198, "Miniscule_Mailemental_in_an_Envelope": 185846, "Perfidious_Projector": 242403, "Variable_Pulse_Lightning_Capacitor": 171640, "Chaotic_Nethergate": 246825, "Vanquished_Clutches_of_Yogg_Saron": 156458, "Voidglass_Kris": 237728}, "simulated_steps": [723, 710, 704, 691, 684], "sorted_data_keys": ["Astral_Antenna", "Arazs_Ritual_Forge", "Diamantine_Voidcore_Prepull_NoMana_Weapon", "Diamantine_Voidcore_Weapon", "Lily_of_the_Eternal_Weave", "Signet_of_the_Priory", "Azhiccaran_Parapodia", "Incorporeal_Essence_Gorger", "Living_Flame", "Empowering_Crystal_of_Anubikkaj", "Diamantine_Voidcore_Prepull_NoMana", "Soleahs_Secret_Technique_Mastery", "Soleahs_Secret_Technique_Versatility", "Soleahs_Secret_Technique_Crit", "Energy_Siphon", "Diamantine_Voidcore", "AraKara_Sacbrood", "Astral_Gladiators_Badge_of_Ferocity", "Gigazaps_Zap_Cap", "Soleahs_Secret_Technique_Haste", "Naazindhris_Mystic_Lash", "Eye_of_the_Broodmother", "Harvesters_Edict_20%", "Mugs_Moxie_Jug", "Voidtouched_Fragment", "Flare_of_the_Heavens", "Mereldars_Toll", "Scale_of_Fates", "House_of_Cards", "Hibernation_Crystal", "Soulbreakers_Sigil", "Essence_Hunters_Eyeglass", "Pandoras_Plea", "Elemental_Focus_Stone", "The_Skull_of_Guldan", "Sunblood_Amethyst", "Automatic_Footbomb_Dispenser", "Astral_Gladiators_Insignia_of_Alacrity", "Screams_of_a_Forgotten_Sky", "Bursting_Lightshard", "Eye_of_Kezan", "Miniscule_Mailemental_in_an_Envelope", "Perfidious_Projector", "Variable_Pulse_Lightning_Capacitor", "Chaotic_Nethergate", "Vanquished_Clutches_of_Yogg_Saron", "Voidglass_Kris"], "last_updated": "2025-08-02"}