{"name": "4T - ar-vf-yogg-cthun-me", "data": {"ME9": {"DPS": 5820061}, "CB1_ME1_QR1_DO1_QS1_ME4": {"DPS": 5816889}, "CB1_VE1_QR1_QO1_QS1_ME4": {"DPS": 5816834}, "CB1_VE1_QR1_VO1_QS1_ME4": {"DPS": 5816600}, "CB1_DE1_QR1_QO1_QS1_ME4": {"DPS": 5816537}, "CB1_VE1_QR1_QO1_MS1_ME4": {"DPS": 5816517}, "CB1_DE1_QR1_QO1_MS1_ME4": {"DPS": 5816497}, "CB1_DE1_MR1_VO1_MS1_ME4": {"DPS": 5816403}, "CB1_DE1_MR1_QO1_QS1_ME4": {"DPS": 5815726}, "CB1_ME8": {"DPS": 5814680}, "CB1_ME1_QR1_VO1_MS1_ME4": {"DPS": 5814625}, "CB1_VE1_MR1_DO1_QS1_ME4": {"DPS": 5814573}, "CB1_ME1_MR1_VO1_MS1_ME4": {"DPS": 5814545}, "CB1_DE1_QR1_VO1_QS1_ME4": {"DPS": 5814531}, "CB1_ME1_MR1_QO1_QS1_ME4": {"DPS": 5814504}, "CB1_DE1_MR1_QO1_MS1_ME4": {"DPS": 5814412}, "CB1_ME1_QR1_QO1_QS1_ME4": {"DPS": 5813984}, "CB1_VE1_MR1_DO1_MS1_ME4": {"DPS": 5813938}, "CB1_VE1_MR1_VO1_MS1_ME4": {"DPS": 5813647}, "CB1_DE1_QR1_DO1_QS1_ME4": {"DPS": 5813317}, "CB1_ME1_QR1_VO1_QS1_ME4": {"DPS": 5813295}, "CB1_ME1_QR1_QO1_MS1_ME4": {"DPS": 5813068}, "CB1_DE1_QR1_VO1_MS1_ME4": {"DPS": 5812959}, "CB1_VE1_QR1_DO1_MS1_ME4": {"DPS": 5812912}, "CB1_VE1_QR1_VO1_MS1_ME4": {"DPS": 5812791}, "CB1_DE1_MR1_DO1_MS1_ME4": {"DPS": 5812268}, "CB1_ME1_MR1_QO1_MS1_ME4": {"DPS": 5811925}, "CB1_VE1_MR1_VO1_QS1_ME4": {"DPS": 5811874}, "CB1_VE1_QR1_DO1_QS1_ME4": {"DPS": 5811763}, "CB1_VE1_MR1_QO1_QS1_ME4": {"DPS": 5811665}, "CB1_ME1_MR1_DO1_QS1_ME4": {"DPS": 5811209}, "CB1_DE1_MR1_VO1_QS1_ME4": {"DPS": 5811134}, "CB1_ME1_MR1_VO1_QS1_ME4": {"DPS": 5810926}, "CB1_DE1_QR1_DO1_MS1_ME4": {"DPS": 5810603}, "CB1_DE1_QR1_VO1_QS1_QO4": {"DPS": 5810523}, "CB1_ME1_QR1_DO1_MS1_ME4": {"DPS": 5810521}, "CB1_VE1_MR1_QO1_MS1_ME4": {"DPS": 5809765}, "CB1_VE1_QR1_VO1_QS1_QO4": {"DPS": 5809685}, "CB1_DE1_MR1_DO1_QS1_ME4": {"DPS": 5809656}, "CB1_ME1_MR1_DO1_MS1_ME4": {"DPS": 5809526}, "CB1_DE1_QR1_QO1_QS1_MA1_ME3": {"DPS": 5809239}, "CB1_VE1_MR1_DO1_QS1_QO4": {"DPS": 5808412}, "CB1_ME1_MR1_DO1_QS1_QO4": {"DPS": 5808165}, "CB1_VE1_MR1_DO1_QS1_QA1_ME3": {"DPS": 5808113}, "CB1_VE1_MR1_QO1_QS1_QA1_ME3": {"DPS": 5807244}, "CB1_DE1_QR1_QO1_MS1_MA1_ME3": {"DPS": 5807125}, "CB1_ME1_QR1_DO1_QS1_QO4": {"DPS": 5807009}, "CB1_ME1_QR1_DO1_QS1_MA1_ME3": {"DPS": 5806719}, "CB1_ME1_QR1_QO1_QS1_QO4": {"DPS": 5806684}, "CB1_DE1_QR1_DO1_QS1_QA1_ME3": {"DPS": 5806657}, "CB1_ME1_QR1_QO1_QS1_MA1_ME3": {"DPS": 5806643}, "CB1_DE1_QR1_QO1_MS1_QO4": {"DPS": 5806393}, "CB1_ME1_QR1_VO1_QS1_QO4": {"DPS": 5806375}, "CB1_DE1_QR1_QO1_QS1_QO4": {"DPS": 5806312}, "CB1_DE1_QR1_QO1_MS1_QA1_ME3": {"DPS": 5806004}, "CB1_VE1_MR1_DO1_MS1_QA1_ME3": {"DPS": 5805963}, "CB1_DE1_QR1_VO1_QS1_MA1_ME3": {"DPS": 5805945}, "CB1_DE1_MR1_VO1_MS1_MA1_ME3": {"DPS": 5805824}, "CB1_DE1_QR1_VO1_QS1_QA1_ME3": {"DPS": 5805773}, "CB1_DE1_QR1_DO1_QS1_QO4": {"DPS": 5805643}, "CB1_ME1_QR1_QO1_QS1_QA1_ME3": {"DPS": 5805537}, "CB1_DE1_MR1_QO1_MS1_MA1_ME3": {"DPS": 5805532}, "CB1_VE1_MR1_VO1_QS1_QA1_ME3": {"DPS": 5805489}, "CB1_ME1_MR1_QO1_MS1_QO4": {"DPS": 5805428}, "CB1_DE1_MR1_QO1_QS1_QO4": {"DPS": 5805403}, "CB1_ME1_QR1_DO1_QS1_QA1_ME3": {"DPS": 5805149}, "CB1_DE1_MR1_VO1_QS1_QA1_ME3": {"DPS": 5805082}, "CB1_DE1_QR1_VO1_MS1_QA1_ME3": {"DPS": 5805041}, "CB1_VE1_QR1_QO1_QS1_QO4": {"DPS": 5805041}, "CB1_VE1_QR1_QO1_MS1_QO4": {"DPS": 5805022}, "CB1_DE1_MR1_DO1_MS1_MA1_ME3": {"DPS": 5805020}, "CB1_VE1_MR1_QO1_QS1_MA1_ME3": {"DPS": 5805019}, "CB1_DE1_QR1_QO1_QS1_QA1_ME3": {"DPS": 5804878}, "CB1_VE1_MR1_QO1_QS1_QO4": {"DPS": 5804800}, "CB1_VE1_QR1_QO1_QS1_MA1_ME3": {"DPS": 5804628}, "CB1_VE1_MR1_QO1_MS1_QO4": {"DPS": 5804611}, "CB1_VE1_QR1_VO1_QS1_MA1_ME3": {"DPS": 5804552}, "CB1_VE1_QR1_DO1_QS1_QO4": {"DPS": 5804535}, "CB1_DE1_MR1_QO1_QS1_MA1_ME3": {"DPS": 5804391}, "CB1_VE1_MR1_QO1_MS1_QA1_ME3": {"DPS": 5804195}, "CB1_DE1_QR1_DO1_QS1_MA1_ME3": {"DPS": 5804179}, "CB1_ME1_QR1_VO1_QS1_QA1_ME3": {"DPS": 5804174}, "CB1_DE1_MR1_DO1_QS1_QA1_ME3": {"DPS": 5804169}, "CB1_ME1_QR1_DO1_MS1_QO4": {"DPS": 5804144}, "CB1_ME1_QR1_VO1_MS1_QO4": {"DPS": 5804135}, "CB1_ME1_QR1_QO1_MS1_QO4": {"DPS": 5804062}, "CB1_ME1_MR1_DO1_QS1_QA1_ME3": {"DPS": 5804033}, "CB1_DE1_QR1_DO1_MS1_QO4": {"DPS": 5803998}, "CB1_ME1_QR1_DO1_MS1_QA1_ME3": {"DPS": 5803994}, "CB1_DE1_MR1_QO1_QS1_QA1_ME3": {"DPS": 5803972}, "CB1_DE1_MR1_DO1_QS1_QO4": {"DPS": 5803960}, "CB1_ME1_QR1_QO1_MS1_MA1_ME3": {"DPS": 5803954}, "CB1_DE1_MR1_DO1_MS1_QO4": {"DPS": 5803886}, "CB1_VE1_QR1_VO1_MS1_MA1_ME3": {"DPS": 5803814}, "CB1_DE1_MR1_QO1_MS1_QO4": {"DPS": 5803714}, "CB1_ME1_MR1_QO1_QS1_QO4": {"DPS": 5803625}, "CB1_DE1_QR1_VO1_MS1_QO4": {"DPS": 5803548}, "CB1_VE1_QR1_QO1_MS1_QA1_ME3": {"DPS": 5803521}, "CB1_DE1_MR1_VO1_MS1_QO4": {"DPS": 5803474}, "CB1_DE1_QR1_DO1_MS1_QA1_ME3": {"DPS": 5803442}, "CB1_ME1_MR1_VO1_QS1_MA1_ME3": {"DPS": 5803426}, "CB1_ME1_QR1_QO1_MS1_QA1_ME3": {"DPS": 5803342}, "CB1_DE1_MR1_VO1_QS1_QO4": {"DPS": 5803331}, "CB1_ME1_QR1_VO1_MS1_QA1_ME3": {"DPS": 5803249}, "CB1_VE1_QR1_DO1_MS1_MA1_ME3": {"DPS": 5803193}, "CB1_ME1_MR1_QO1_QS1_QA1_ME3": {"DPS": 5802998}, "CB1_DE1_MR1_VO1_QS1_MA1_ME3": {"DPS": 5802896}, "CB1_ME1_MR1_DO1_MS1_MA1_ME3": {"DPS": 5802791}, "CB1_VE1_MR1_DO1_MS1_MA1_ME3": {"DPS": 5802754}, "CB1_VE1_QR1_VO1_QS1_QA1_ME3": {"DPS": 5802729}, "CB1_ME1_MR1_VO1_MS1_QO4": {"DPS": 5802712}, "CB1_VE1_QR1_VO1_MS1_QO4": {"DPS": 5802702}, "CB1_VE1_MR1_VO1_MS1_MA1_ME3": {"DPS": 5802684}, "CB1_VE1_QR1_VO1_MS1_QA1_ME3": {"DPS": 5802514}, "CB1_DE1_QR1_DO1_MS1_MA1_ME3": {"DPS": 5802393}, "CB1_VE1_QR1_QO1_QS1_QA1_ME3": {"DPS": 5802352}, "CB1_VE1_MR1_VO1_MS1_QA1_ME3": {"DPS": 5802283}, "CB1_DE1_MR1_DO1_QS1_MA1_ME3": {"DPS": 5802243}, "CB1_ME1_MR1_DO1_MS1_QO4": {"DPS": 5802188}, "CB1_ME1_MR1_DO1_MS1_QA1_ME3": {"DPS": 5802181}, "CB1_ME1_MR1_VO1_QS1_QA1_ME3": {"DPS": 5802162}, "CB1_VE1_MR1_DO1_QS1_MA1_ME3": {"DPS": 5802124}, "CB1_VE1_QR1_DO1_QS1_MA1_ME3": {"DPS": 5802096}, "CB1_VE1_QR1_DO1_MS1_QO4": {"DPS": 5802094}, "CB1_VE1_MR1_VO1_QS1_QO4": {"DPS": 5801738}, "CB1_VE1_MR1_DO1_MS1_QO4": {"DPS": 5801737}, "CB1_ME1_MR1_VO1_QS1_QO4": {"DPS": 5801618}, "CB1_VE1_MR1_VO1_MS1_QO4": {"DPS": 5801615}, "CB1_DE1_MR1_VO1_MS1_QA1_ME3": {"DPS": 5801564}, "CB1_ME1_QR1_VO1_QS1_MA1_QO3": {"DPS": 5801502}, "CB1_VE1_QR1_DO1_MS1_QA1_ME3": {"DPS": 5801493}, "CB1_DE1_MR1_DO1_MS1_QA1_ME3": {"DPS": 5801448}, "CB1_ME1_MR1_QO1_QS1_MA1_ME3": {"DPS": 5801205}, "CB1_DE1_MR1_QO1_MS1_QA1_ME3": {"DPS": 5801149}, "CB1_ME1_MR1_VO1_MS1_QA1_ME3": {"DPS": 5801119}, "CB1_ME1_QR1_QO1_QS1_QA1_QO3": {"DPS": 5800883}, "CB1_ME1_QR1_DO1_MS1_MA1_ME3": {"DPS": 5800666}, "CB1_ME1_MR1_VO1_MS1_MA1_ME3": {"DPS": 5800626}, "CB1_VE1_MR1_QO1_QS1_QA1_QO3": {"DPS": 5800626}, "CB1_DE1_MR1_DO1_QS1_QA1_QO3": {"DPS": 5800577}, "CB1_ME1_MR1_QO1_MS1_MA1_ME3": {"DPS": 5800502}, "CB1_VE1_MR1_VO1_QS1_MA1_ME3": {"DPS": 5800301}, "CB1_VE1_QR1_QO1_MS1_MA1_ME3": {"DPS": 5800285}, "CB1_ME1_QR1_VO1_MS1_MA1_ME3": {"DPS": 5800053}, "CB1_ME1_QR1_QO1_QS1_MA1_QO3": {"DPS": 5799926}, "CB1_DE1_QR1_DO1_QS1_QA1_QO3": {"DPS": 5799768}, "CB1_ME1_MR1_DO1_QS1_MA1_ME3": {"DPS": 5799613}, "CB1_ME1_QR1_VO1_QS1_MA1_ME3": {"DPS": 5799495}, "CB1_ME1_MR1_QO1_MS1_QA1_ME3": {"DPS": 5799306}, "CB1_DE1_MR1_QO1_QS1_QA1_QO3": {"DPS": 5799271}, "CB1_ME1_MR1_QO1_QS1_QA1_QO3": {"DPS": 5799173}, "CB1_DE1_QR1_QO1_MS1_QA1_QO3": {"DPS": 5799122}, "CB1_ME1_MR1_QO1_MS1_QA1_QO3": {"DPS": 5799092}, "CB1_VE1_QR1_DO1_QS1_QA1_ME3": {"DPS": 5799069}, "CB1_ME1_QR1_DO1_QS1_QA1_QO3": {"DPS": 5799041}, "CB1_DE1_QR1_VO1_MS1_QA1_QO3": {"DPS": 5799027}, "CB1_VE1_QR1_DO1_MS1_QA1_QO3": {"DPS": 5799022}, "CB1_ME1_MR1_DO1_QS1_MA1_QO3": {"DPS": 5798919}, "CB1_VE1_QR1_QO1_QS1_MA1_QO3": {"DPS": 5798879}, "CB1_DE1_QR1_DO1_QS1_MA1_QO3": {"DPS": 5798693}, "CB1_ME1_MR1_QO1_QS1_MA1_QO3": {"DPS": 5798508}, "CB1_ME1_QR1_QO1_MS1_MA1_QO3": {"DPS": 5798504}, "CB1_VE1_MR1_QO1_MS1_MA1_ME3": {"DPS": 5798453}, "CB1_VE1_MR1_VO1_QS1_QA1_QO3": {"DPS": 5798301}, "CB1_DE1_QR1_VO1_MS1_MA1_ME3": {"DPS": 5798296}, "CB1_DE1_QR1_VO1_QS1_QA1_QO3": {"DPS": 5798260}, "CB1_DE1_MR1_VO1_QS1_QA1_QO3": {"DPS": 5798220}, "CB1_VE1_QR1_QO1_QS1_QA1_QO3": {"DPS": 5798069}, "CB1_VE1_MR1_QO1_QS1_MA1_QO3": {"DPS": 5797989}, "CB1_DE1_MR1_QO1_MS1_QA1_QO3": {"DPS": 5797715}, "CB1_ME1_QR1_VO1_QS1_QA1_QO3": {"DPS": 5797543}, "CB1_VE1_QR1_VO1_MS1_QA1_QO3": {"DPS": 5797538}, "CB1_ME1_QR1_QO1_MS1_QA1_QO3": {"DPS": 5797530}, "CB1_VE1_QR1_DO1_MS1_MA1_QO3": {"DPS": 5797409}, "CB1_VE1_MR1_QO1_MS1_QA1_QO3": {"DPS": 5797330}, "CB1_VE1_MR1_VO1_QS1_MA1_QO3": {"DPS": 5796870}, "CB1_ME1_MR1_VO1_QS1_QA1_QO3": {"DPS": 5796810}, "CB1_ME1_QR1_VO1_MS1_QA1_QO3": {"DPS": 5796787}, "CB1_VE1_MR1_DO1_MS1_QA1_QO3": {"DPS": 5796743}, "CB1_DE1_MR1_DO1_QS1_MA1_QO3": {"DPS": 5796609}, "CB1_VE1_QR1_VO1_QS1_QA1_QO3": {"DPS": 5796602}, "CB1_VE1_QR1_QO1_MS1_MA1_QO3": {"DPS": 5796509}, "CB1_VE1_MR1_DO1_QS1_QA1_QO3": {"DPS": 5796316}, "CB1_DE1_QR1_QO1_QS1_MA1_QO3": {"DPS": 5796139}, "CB1_VE1_QR1_VO1_MS1_MA1_QO3": {"DPS": 5796139}, "CB1_VE1_QR1_VO1_QS1_MA1_QO3": {"DPS": 5796124}, "CB1_DE1_QR1_QO1_MS1_MA1_QO3": {"DPS": 5795961}, "CB1_DE1_MR1_VO1_MS1_QA1_QO3": {"DPS": 5795892}, "CB1_ME1_QR1_DO1_MS1_QA1_QO3": {"DPS": 5795702}, "CB1_ME1_MR1_QO1_MS1_MA1_QO3": {"DPS": 5795599}, "CB1_DE1_MR1_QO1_QS1_MA1_QO3": {"DPS": 5795589}, "CB1_VE1_MR1_VO1_MS1_QA1_QO3": {"DPS": 5795457}, "CB1_VE1_QR1_DO1_QS1_MA1_QO3": {"DPS": 5795440}, "CB1_ME1_QR1_DO1_MS1_MA1_QO3": {"DPS": 5795287}, "CB1_ME1_MR1_DO1_QS1_QA1_QO3": {"DPS": 5795228}, "CB1_ME1_MR1_VO1_QS1_MA1_QO3": {"DPS": 5795221}, "CB1_VE1_QR1_DO1_QS1_QA1_QO3": {"DPS": 5795102}, "QO9": {"DPS": 5795081}, "CB1_DE1_MR1_VO1_MS1_MA1_QO3": {"DPS": 5795080}, "CB1_QO8": {"DPS": 5794991}, "CB1_ME1_QR1_VO1_MS1_MA1_QO3": {"DPS": 5794944}, "CB1_VE1_MR1_VO1_MS1_MA1_QO3": {"DPS": 5794881}, "CB1_ME1_MR1_DO1_MS1_MA1_QO3": {"DPS": 5794856}, "CB1_DE1_QR1_DO1_MS1_QA1_QO3": {"DPS": 5794715}, "CB1_DE1_QR1_VO1_MS1_MA1_QO3": {"DPS": 5794319}, "CB1_ME1_MR1_VO1_MS1_MA1_QO3": {"DPS": 5794291}, "CB1_VE1_MR1_DO1_QS1_MA1_QO3": {"DPS": 5794196}, "CB1_DE1_MR1_DO1_MS1_MA1_QO3": {"DPS": 5794195}, "CB1_ME1_MR1_DO1_MS1_QA1_QO3": {"DPS": 5794001}, "CB1_DE1_MR1_VO1_QS1_MA1_QO3": {"DPS": 5793970}, "CB1_DE1_MR1_DO1_MS1_QA1_QO3": {"DPS": 5793922}, "CB1_DE1_QR1_VO1_QS1_MA1_QO3": {"DPS": 5793838}, "CB1_DE1_QR1_QO1_QS1_QA1_QO3": {"DPS": 5793524}, "CB1_ME1_QR1_DO1_QS1_MA1_QO3": {"DPS": 5793286}, "CB1_VE1_QR1_QO1_MS1_QA1_QO3": {"DPS": 5793219}, "CB1_VE1_MR1_DO1_MS1_MA1_QO3": {"DPS": 5793103}, "CB1_VE1_MR1_QO1_MS1_MA1_QO3": {"DPS": 5792844}, "CB1_ME1_MR1_VO1_MS1_QA1_QO3": {"DPS": 5792382}, "CB1_DE1_MR1_QO1_MS1_MA1_QO3": {"DPS": 5791997}, "CB1_DE1_QR1_DO1_MS1_MA1_QO3": {"DPS": 5791318}, "Base": {"DPS": 5670317}}, "ids": {"ME9": null, "CB1_ME1_QR1_DO1_QS1_ME4": null, "CB1_VE1_QR1_QO1_QS1_ME4": null, "CB1_VE1_QR1_VO1_QS1_ME4": null, "CB1_DE1_QR1_QO1_QS1_ME4": null, "CB1_VE1_QR1_QO1_MS1_ME4": null, "CB1_DE1_QR1_QO1_MS1_ME4": null, "CB1_DE1_MR1_VO1_MS1_ME4": null, "CB1_DE1_MR1_QO1_QS1_ME4": null, "CB1_ME8": null, "CB1_ME1_QR1_VO1_MS1_ME4": null, "CB1_VE1_MR1_DO1_QS1_ME4": null, "CB1_ME1_MR1_VO1_MS1_ME4": null, "CB1_DE1_QR1_VO1_QS1_ME4": null, "CB1_ME1_MR1_QO1_QS1_ME4": null, "CB1_DE1_MR1_QO1_MS1_ME4": null, "CB1_ME1_QR1_QO1_QS1_ME4": null, "CB1_VE1_MR1_DO1_MS1_ME4": null, "CB1_VE1_MR1_VO1_MS1_ME4": null, "CB1_DE1_QR1_DO1_QS1_ME4": null, "CB1_ME1_QR1_VO1_QS1_ME4": null, "CB1_ME1_QR1_QO1_MS1_ME4": null, "CB1_DE1_QR1_VO1_MS1_ME4": null, "CB1_VE1_QR1_DO1_MS1_ME4": null, "CB1_VE1_QR1_VO1_MS1_ME4": null, "CB1_DE1_MR1_DO1_MS1_ME4": null, "CB1_ME1_MR1_QO1_MS1_ME4": null, "CB1_VE1_MR1_VO1_QS1_ME4": null, "CB1_VE1_QR1_DO1_QS1_ME4": null, "CB1_VE1_MR1_QO1_QS1_ME4": null, "CB1_ME1_MR1_DO1_QS1_ME4": null, "CB1_DE1_MR1_VO1_QS1_ME4": null, "CB1_ME1_MR1_VO1_QS1_ME4": null, "CB1_DE1_QR1_DO1_MS1_ME4": null, "CB1_DE1_QR1_VO1_QS1_QO4": null, "CB1_ME1_QR1_DO1_MS1_ME4": null, "CB1_VE1_MR1_QO1_MS1_ME4": null, "CB1_VE1_QR1_VO1_QS1_QO4": null, "CB1_DE1_MR1_DO1_QS1_ME4": null, "CB1_ME1_MR1_DO1_MS1_ME4": null, "CB1_DE1_QR1_QO1_QS1_MA1_ME3": null, "CB1_VE1_MR1_DO1_QS1_QO4": null, "CB1_ME1_MR1_DO1_QS1_QO4": null, "CB1_VE1_MR1_DO1_QS1_QA1_ME3": null, "CB1_VE1_MR1_QO1_QS1_QA1_ME3": null, "CB1_DE1_QR1_QO1_MS1_MA1_ME3": null, "CB1_ME1_QR1_DO1_QS1_QO4": null, "CB1_ME1_QR1_DO1_QS1_MA1_ME3": null, "CB1_ME1_QR1_QO1_QS1_QO4": null, "CB1_DE1_QR1_DO1_QS1_QA1_ME3": null, "CB1_ME1_QR1_QO1_QS1_MA1_ME3": null, "CB1_DE1_QR1_QO1_MS1_QO4": null, "CB1_ME1_QR1_VO1_QS1_QO4": null, "CB1_DE1_QR1_QO1_QS1_QO4": null, "CB1_DE1_QR1_QO1_MS1_QA1_ME3": null, "CB1_VE1_MR1_DO1_MS1_QA1_ME3": null, "CB1_DE1_QR1_VO1_QS1_MA1_ME3": null, "CB1_DE1_MR1_VO1_MS1_MA1_ME3": null, "CB1_DE1_QR1_VO1_QS1_QA1_ME3": null, "CB1_DE1_QR1_DO1_QS1_QO4": null, "CB1_ME1_QR1_QO1_QS1_QA1_ME3": null, "CB1_DE1_MR1_QO1_MS1_MA1_ME3": null, "CB1_VE1_MR1_VO1_QS1_QA1_ME3": null, "CB1_ME1_MR1_QO1_MS1_QO4": null, "CB1_DE1_MR1_QO1_QS1_QO4": null, "CB1_ME1_QR1_DO1_QS1_QA1_ME3": null, "CB1_DE1_MR1_VO1_QS1_QA1_ME3": null, "CB1_DE1_QR1_VO1_MS1_QA1_ME3": null, "CB1_VE1_QR1_QO1_QS1_QO4": null, "CB1_VE1_QR1_QO1_MS1_QO4": null, "CB1_DE1_MR1_DO1_MS1_MA1_ME3": null, "CB1_VE1_MR1_QO1_QS1_MA1_ME3": null, "CB1_DE1_QR1_QO1_QS1_QA1_ME3": null, "CB1_VE1_MR1_QO1_QS1_QO4": null, "CB1_VE1_QR1_QO1_QS1_MA1_ME3": null, "CB1_VE1_MR1_QO1_MS1_QO4": null, "CB1_VE1_QR1_VO1_QS1_MA1_ME3": null, "CB1_VE1_QR1_DO1_QS1_QO4": null, "CB1_DE1_MR1_QO1_QS1_MA1_ME3": null, "CB1_VE1_MR1_QO1_MS1_QA1_ME3": null, "CB1_DE1_QR1_DO1_QS1_MA1_ME3": null, "CB1_ME1_QR1_VO1_QS1_QA1_ME3": null, "CB1_DE1_MR1_DO1_QS1_QA1_ME3": null, "CB1_ME1_QR1_DO1_MS1_QO4": null, "CB1_ME1_QR1_VO1_MS1_QO4": null, "CB1_ME1_QR1_QO1_MS1_QO4": null, "CB1_ME1_MR1_DO1_QS1_QA1_ME3": null, "CB1_DE1_QR1_DO1_MS1_QO4": null, "CB1_ME1_QR1_DO1_MS1_QA1_ME3": null, "CB1_DE1_MR1_QO1_QS1_QA1_ME3": null, "CB1_DE1_MR1_DO1_QS1_QO4": null, "CB1_ME1_QR1_QO1_MS1_MA1_ME3": null, "CB1_DE1_MR1_DO1_MS1_QO4": null, "CB1_VE1_QR1_VO1_MS1_MA1_ME3": null, "CB1_DE1_MR1_QO1_MS1_QO4": null, "CB1_ME1_MR1_QO1_QS1_QO4": null, "CB1_DE1_QR1_VO1_MS1_QO4": null, "CB1_VE1_QR1_QO1_MS1_QA1_ME3": null, "CB1_DE1_MR1_VO1_MS1_QO4": null, "CB1_DE1_QR1_DO1_MS1_QA1_ME3": null, "CB1_ME1_MR1_VO1_QS1_MA1_ME3": null, "CB1_ME1_QR1_QO1_MS1_QA1_ME3": null, "CB1_DE1_MR1_VO1_QS1_QO4": null, "CB1_ME1_QR1_VO1_MS1_QA1_ME3": null, "CB1_VE1_QR1_DO1_MS1_MA1_ME3": null, "CB1_ME1_MR1_QO1_QS1_QA1_ME3": null, "CB1_DE1_MR1_VO1_QS1_MA1_ME3": null, "CB1_ME1_MR1_DO1_MS1_MA1_ME3": null, "CB1_VE1_MR1_DO1_MS1_MA1_ME3": null, "CB1_VE1_QR1_VO1_QS1_QA1_ME3": null, "CB1_ME1_MR1_VO1_MS1_QO4": null, "CB1_VE1_QR1_VO1_MS1_QO4": null, "CB1_VE1_MR1_VO1_MS1_MA1_ME3": null, "CB1_VE1_QR1_VO1_MS1_QA1_ME3": null, "CB1_DE1_QR1_DO1_MS1_MA1_ME3": null, "CB1_VE1_QR1_QO1_QS1_QA1_ME3": null, "CB1_VE1_MR1_VO1_MS1_QA1_ME3": null, "CB1_DE1_MR1_DO1_QS1_MA1_ME3": null, "CB1_ME1_MR1_DO1_MS1_QO4": null, "CB1_ME1_MR1_DO1_MS1_QA1_ME3": null, "CB1_ME1_MR1_VO1_QS1_QA1_ME3": null, "CB1_VE1_MR1_DO1_QS1_MA1_ME3": null, "CB1_VE1_QR1_DO1_QS1_MA1_ME3": null, "CB1_VE1_QR1_DO1_MS1_QO4": null, "CB1_VE1_MR1_VO1_QS1_QO4": null, "CB1_VE1_MR1_DO1_MS1_QO4": null, "CB1_ME1_MR1_VO1_QS1_QO4": null, "CB1_VE1_MR1_VO1_MS1_QO4": null, "CB1_DE1_MR1_VO1_MS1_QA1_ME3": null, "CB1_ME1_QR1_VO1_QS1_MA1_QO3": null, "CB1_VE1_QR1_DO1_MS1_QA1_ME3": null, "CB1_DE1_MR1_DO1_MS1_QA1_ME3": null, "CB1_ME1_MR1_QO1_QS1_MA1_ME3": null, "CB1_DE1_MR1_QO1_MS1_QA1_ME3": null, "CB1_ME1_MR1_VO1_MS1_QA1_ME3": null, "CB1_ME1_QR1_QO1_QS1_QA1_QO3": null, "CB1_ME1_QR1_DO1_MS1_MA1_ME3": null, "CB1_ME1_MR1_VO1_MS1_MA1_ME3": null, "CB1_VE1_MR1_QO1_QS1_QA1_QO3": null, "CB1_DE1_MR1_DO1_QS1_QA1_QO3": null, "CB1_ME1_MR1_QO1_MS1_MA1_ME3": null, "CB1_VE1_MR1_VO1_QS1_MA1_ME3": null, "CB1_VE1_QR1_QO1_MS1_MA1_ME3": null, "CB1_ME1_QR1_VO1_MS1_MA1_ME3": null, "CB1_ME1_QR1_QO1_QS1_MA1_QO3": null, "CB1_DE1_QR1_DO1_QS1_QA1_QO3": null, "CB1_ME1_MR1_DO1_QS1_MA1_ME3": null, "CB1_ME1_QR1_VO1_QS1_MA1_ME3": null, "CB1_ME1_MR1_QO1_MS1_QA1_ME3": null, "CB1_DE1_MR1_QO1_QS1_QA1_QO3": null, "CB1_ME1_MR1_QO1_QS1_QA1_QO3": null, "CB1_DE1_QR1_QO1_MS1_QA1_QO3": null, "CB1_ME1_MR1_QO1_MS1_QA1_QO3": null, "CB1_VE1_QR1_DO1_QS1_QA1_ME3": null, "CB1_ME1_QR1_DO1_QS1_QA1_QO3": null, "CB1_DE1_QR1_VO1_MS1_QA1_QO3": null, "CB1_VE1_QR1_DO1_MS1_QA1_QO3": null, "CB1_ME1_MR1_DO1_QS1_MA1_QO3": null, "CB1_VE1_QR1_QO1_QS1_MA1_QO3": null, "CB1_DE1_QR1_DO1_QS1_MA1_QO3": null, "CB1_ME1_MR1_QO1_QS1_MA1_QO3": null, "CB1_ME1_QR1_QO1_MS1_MA1_QO3": null, "CB1_VE1_MR1_QO1_MS1_MA1_ME3": null, "CB1_VE1_MR1_VO1_QS1_QA1_QO3": null, "CB1_DE1_QR1_VO1_MS1_MA1_ME3": null, "CB1_DE1_QR1_VO1_QS1_QA1_QO3": null, "CB1_DE1_MR1_VO1_QS1_QA1_QO3": null, "CB1_VE1_QR1_QO1_QS1_QA1_QO3": null, "CB1_VE1_MR1_QO1_QS1_MA1_QO3": null, "CB1_DE1_MR1_QO1_MS1_QA1_QO3": null, "CB1_ME1_QR1_VO1_QS1_QA1_QO3": null, "CB1_VE1_QR1_VO1_MS1_QA1_QO3": null, "CB1_ME1_QR1_QO1_MS1_QA1_QO3": null, "CB1_VE1_QR1_DO1_MS1_MA1_QO3": null, "CB1_VE1_MR1_QO1_MS1_QA1_QO3": null, "CB1_VE1_MR1_VO1_QS1_MA1_QO3": null, "CB1_ME1_MR1_VO1_QS1_QA1_QO3": null, "CB1_ME1_QR1_VO1_MS1_QA1_QO3": null, "CB1_VE1_MR1_DO1_MS1_QA1_QO3": null, "CB1_DE1_MR1_DO1_QS1_MA1_QO3": null, "CB1_VE1_QR1_VO1_QS1_QA1_QO3": null, "CB1_VE1_QR1_QO1_MS1_MA1_QO3": null, "CB1_VE1_MR1_DO1_QS1_QA1_QO3": null, "CB1_DE1_QR1_QO1_QS1_MA1_QO3": null, "CB1_VE1_QR1_VO1_MS1_MA1_QO3": null, "CB1_VE1_QR1_VO1_QS1_MA1_QO3": null, "CB1_DE1_QR1_QO1_MS1_MA1_QO3": null, "CB1_DE1_MR1_VO1_MS1_QA1_QO3": null, "CB1_ME1_QR1_DO1_MS1_QA1_QO3": null, "CB1_ME1_MR1_QO1_MS1_MA1_QO3": null, "CB1_DE1_MR1_QO1_QS1_MA1_QO3": null, "CB1_VE1_MR1_VO1_MS1_QA1_QO3": null, "CB1_VE1_QR1_DO1_QS1_MA1_QO3": null, "CB1_ME1_QR1_DO1_MS1_MA1_QO3": null, "CB1_ME1_MR1_DO1_QS1_QA1_QO3": null, "CB1_ME1_MR1_VO1_QS1_MA1_QO3": null, "CB1_VE1_QR1_DO1_QS1_QA1_QO3": null, "QO9": null, "CB1_DE1_MR1_VO1_MS1_MA1_QO3": null, "CB1_QO8": null, "CB1_ME1_QR1_VO1_MS1_MA1_QO3": null, "CB1_VE1_MR1_VO1_MS1_MA1_QO3": null, "CB1_ME1_MR1_DO1_MS1_MA1_QO3": null, "CB1_DE1_QR1_DO1_MS1_QA1_QO3": null, "CB1_DE1_QR1_VO1_MS1_MA1_QO3": null, "CB1_ME1_MR1_VO1_MS1_MA1_QO3": null, "CB1_VE1_MR1_DO1_QS1_MA1_QO3": null, "CB1_DE1_MR1_DO1_MS1_MA1_QO3": null, "CB1_ME1_MR1_DO1_MS1_QA1_QO3": null, "CB1_DE1_MR1_VO1_QS1_MA1_QO3": null, "CB1_DE1_MR1_DO1_MS1_QA1_QO3": null, "CB1_DE1_QR1_VO1_QS1_MA1_QO3": null, "CB1_DE1_QR1_QO1_QS1_QA1_QO3": null, "CB1_ME1_QR1_DO1_QS1_MA1_QO3": null, "CB1_VE1_QR1_QO1_MS1_QA1_QO3": null, "CB1_VE1_MR1_DO1_MS1_MA1_QO3": null, "CB1_VE1_MR1_QO1_MS1_MA1_QO3": null, "CB1_ME1_MR1_VO1_MS1_QA1_QO3": null, "CB1_DE1_MR1_QO1_MS1_MA1_QO3": null, "CB1_DE1_QR1_DO1_MS1_MA1_QO3": null}, "simulated_steps": ["DPS"], "sorted_data_keys": ["ME9", "CB1_ME1_QR1_DO1_QS1_ME4", "CB1_VE1_QR1_QO1_QS1_ME4", "CB1_VE1_QR1_VO1_QS1_ME4", "CB1_DE1_QR1_QO1_QS1_ME4", "CB1_VE1_QR1_QO1_MS1_ME4", "CB1_DE1_QR1_QO1_MS1_ME4", "CB1_DE1_MR1_VO1_MS1_ME4", "CB1_DE1_MR1_QO1_QS1_ME4", "CB1_ME8", "CB1_ME1_QR1_VO1_MS1_ME4", "CB1_VE1_MR1_DO1_QS1_ME4", "CB1_ME1_MR1_VO1_MS1_ME4", "CB1_DE1_QR1_VO1_QS1_ME4", "CB1_ME1_MR1_QO1_QS1_ME4", "CB1_DE1_MR1_QO1_MS1_ME4", "CB1_ME1_QR1_QO1_QS1_ME4", "CB1_VE1_MR1_DO1_MS1_ME4", "CB1_VE1_MR1_VO1_MS1_ME4", "CB1_DE1_QR1_DO1_QS1_ME4", "CB1_ME1_QR1_VO1_QS1_ME4", "CB1_ME1_QR1_QO1_MS1_ME4", "CB1_DE1_QR1_VO1_MS1_ME4", "CB1_VE1_QR1_DO1_MS1_ME4", "CB1_VE1_QR1_VO1_MS1_ME4", "CB1_DE1_MR1_DO1_MS1_ME4", "CB1_ME1_MR1_QO1_MS1_ME4", "CB1_VE1_MR1_VO1_QS1_ME4", "CB1_VE1_QR1_DO1_QS1_ME4", "CB1_VE1_MR1_QO1_QS1_ME4", "CB1_ME1_MR1_DO1_QS1_ME4", "CB1_DE1_MR1_VO1_QS1_ME4", "CB1_ME1_MR1_VO1_QS1_ME4", "CB1_DE1_QR1_DO1_MS1_ME4", "CB1_DE1_QR1_VO1_QS1_QO4", "CB1_ME1_QR1_DO1_MS1_ME4", "CB1_VE1_MR1_QO1_MS1_ME4", "CB1_VE1_QR1_VO1_QS1_QO4", "CB1_DE1_MR1_DO1_QS1_ME4", "CB1_ME1_MR1_DO1_MS1_ME4", "CB1_DE1_QR1_QO1_QS1_MA1_ME3", "CB1_VE1_MR1_DO1_QS1_QO4", "CB1_ME1_MR1_DO1_QS1_QO4", "CB1_VE1_MR1_DO1_QS1_QA1_ME3", "CB1_VE1_MR1_QO1_QS1_QA1_ME3", "CB1_DE1_QR1_QO1_MS1_MA1_ME3", "CB1_ME1_QR1_DO1_QS1_QO4", "CB1_ME1_QR1_DO1_QS1_MA1_ME3", "CB1_ME1_QR1_QO1_QS1_QO4", "CB1_DE1_QR1_DO1_QS1_QA1_ME3", "CB1_ME1_QR1_QO1_QS1_MA1_ME3", "CB1_DE1_QR1_QO1_MS1_QO4", "CB1_ME1_QR1_VO1_QS1_QO4", "CB1_DE1_QR1_QO1_QS1_QO4", "CB1_DE1_QR1_QO1_MS1_QA1_ME3", "CB1_VE1_MR1_DO1_MS1_QA1_ME3", "CB1_DE1_QR1_VO1_QS1_MA1_ME3", "CB1_DE1_MR1_VO1_MS1_MA1_ME3", "CB1_DE1_QR1_VO1_QS1_QA1_ME3", "CB1_DE1_QR1_DO1_QS1_QO4", "CB1_ME1_QR1_QO1_QS1_QA1_ME3", "CB1_DE1_MR1_QO1_MS1_MA1_ME3", "CB1_VE1_MR1_VO1_QS1_QA1_ME3", "CB1_ME1_MR1_QO1_MS1_QO4", "CB1_DE1_MR1_QO1_QS1_QO4", "CB1_ME1_QR1_DO1_QS1_QA1_ME3", "CB1_DE1_MR1_VO1_QS1_QA1_ME3", "CB1_DE1_QR1_VO1_MS1_QA1_ME3", "CB1_VE1_QR1_QO1_QS1_QO4", "CB1_VE1_QR1_QO1_MS1_QO4", "CB1_DE1_MR1_DO1_MS1_MA1_ME3", "CB1_VE1_MR1_QO1_QS1_MA1_ME3", "CB1_DE1_QR1_QO1_QS1_QA1_ME3", "CB1_VE1_MR1_QO1_QS1_QO4", "CB1_VE1_QR1_QO1_QS1_MA1_ME3", "CB1_VE1_MR1_QO1_MS1_QO4", "CB1_VE1_QR1_VO1_QS1_MA1_ME3", "CB1_VE1_QR1_DO1_QS1_QO4", "CB1_DE1_MR1_QO1_QS1_MA1_ME3", "CB1_VE1_MR1_QO1_MS1_QA1_ME3", "CB1_DE1_QR1_DO1_QS1_MA1_ME3", "CB1_ME1_QR1_VO1_QS1_QA1_ME3", "CB1_DE1_MR1_DO1_QS1_QA1_ME3", "CB1_ME1_QR1_DO1_MS1_QO4", "CB1_ME1_QR1_VO1_MS1_QO4", "CB1_ME1_QR1_QO1_MS1_QO4", "CB1_ME1_MR1_DO1_QS1_QA1_ME3", "CB1_DE1_QR1_DO1_MS1_QO4", "CB1_ME1_QR1_DO1_MS1_QA1_ME3", "CB1_DE1_MR1_QO1_QS1_QA1_ME3", "CB1_DE1_MR1_DO1_QS1_QO4", "CB1_ME1_QR1_QO1_MS1_MA1_ME3", "CB1_DE1_MR1_DO1_MS1_QO4", "CB1_VE1_QR1_VO1_MS1_MA1_ME3", "CB1_DE1_MR1_QO1_MS1_QO4", "CB1_ME1_MR1_QO1_QS1_QO4", "CB1_DE1_QR1_VO1_MS1_QO4", "CB1_VE1_QR1_QO1_MS1_QA1_ME3", "CB1_DE1_MR1_VO1_MS1_QO4", "CB1_DE1_QR1_DO1_MS1_QA1_ME3", "CB1_ME1_MR1_VO1_QS1_MA1_ME3", "CB1_ME1_QR1_QO1_MS1_QA1_ME3", "CB1_DE1_MR1_VO1_QS1_QO4", "CB1_ME1_QR1_VO1_MS1_QA1_ME3", "CB1_VE1_QR1_DO1_MS1_MA1_ME3", "CB1_ME1_MR1_QO1_QS1_QA1_ME3", "CB1_DE1_MR1_VO1_QS1_MA1_ME3", "CB1_ME1_MR1_DO1_MS1_MA1_ME3", "CB1_VE1_MR1_DO1_MS1_MA1_ME3", "CB1_VE1_QR1_VO1_QS1_QA1_ME3", "CB1_ME1_MR1_VO1_MS1_QO4", "CB1_VE1_QR1_VO1_MS1_QO4", "CB1_VE1_MR1_VO1_MS1_MA1_ME3", "CB1_VE1_QR1_VO1_MS1_QA1_ME3", "CB1_DE1_QR1_DO1_MS1_MA1_ME3", "CB1_VE1_QR1_QO1_QS1_QA1_ME3", "CB1_VE1_MR1_VO1_MS1_QA1_ME3", "CB1_DE1_MR1_DO1_QS1_MA1_ME3", "CB1_ME1_MR1_DO1_MS1_QO4", "CB1_ME1_MR1_DO1_MS1_QA1_ME3", "CB1_ME1_MR1_VO1_QS1_QA1_ME3", "CB1_VE1_MR1_DO1_QS1_MA1_ME3", "CB1_VE1_QR1_DO1_QS1_MA1_ME3", "CB1_VE1_QR1_DO1_MS1_QO4", "CB1_VE1_MR1_VO1_QS1_QO4", "CB1_VE1_MR1_DO1_MS1_QO4", "CB1_ME1_MR1_VO1_QS1_QO4", "CB1_VE1_MR1_VO1_MS1_QO4", "CB1_DE1_MR1_VO1_MS1_QA1_ME3", "CB1_ME1_QR1_VO1_QS1_MA1_QO3", "CB1_VE1_QR1_DO1_MS1_QA1_ME3", "CB1_DE1_MR1_DO1_MS1_QA1_ME3", "CB1_ME1_MR1_QO1_QS1_MA1_ME3", "CB1_DE1_MR1_QO1_MS1_QA1_ME3", "CB1_ME1_MR1_VO1_MS1_QA1_ME3", "CB1_ME1_QR1_QO1_QS1_QA1_QO3", "CB1_ME1_QR1_DO1_MS1_MA1_ME3", "CB1_ME1_MR1_VO1_MS1_MA1_ME3", "CB1_VE1_MR1_QO1_QS1_QA1_QO3", "CB1_DE1_MR1_DO1_QS1_QA1_QO3", "CB1_ME1_MR1_QO1_MS1_MA1_ME3", "CB1_VE1_MR1_VO1_QS1_MA1_ME3", "CB1_VE1_QR1_QO1_MS1_MA1_ME3", "CB1_ME1_QR1_VO1_MS1_MA1_ME3", "CB1_ME1_QR1_QO1_QS1_MA1_QO3", "CB1_DE1_QR1_DO1_QS1_QA1_QO3", "CB1_ME1_MR1_DO1_QS1_MA1_ME3", "CB1_ME1_QR1_VO1_QS1_MA1_ME3", "CB1_ME1_MR1_QO1_MS1_QA1_ME3", "CB1_DE1_MR1_QO1_QS1_QA1_QO3", "CB1_ME1_MR1_QO1_QS1_QA1_QO3", "CB1_DE1_QR1_QO1_MS1_QA1_QO3", "CB1_ME1_MR1_QO1_MS1_QA1_QO3", "CB1_VE1_QR1_DO1_QS1_QA1_ME3", "CB1_ME1_QR1_DO1_QS1_QA1_QO3", "CB1_DE1_QR1_VO1_MS1_QA1_QO3", "CB1_VE1_QR1_DO1_MS1_QA1_QO3", "CB1_ME1_MR1_DO1_QS1_MA1_QO3", "CB1_VE1_QR1_QO1_QS1_MA1_QO3", "CB1_DE1_QR1_DO1_QS1_MA1_QO3", "CB1_ME1_MR1_QO1_QS1_MA1_QO3", "CB1_ME1_QR1_QO1_MS1_MA1_QO3", "CB1_VE1_MR1_QO1_MS1_MA1_ME3", "CB1_VE1_MR1_VO1_QS1_QA1_QO3", "CB1_DE1_QR1_VO1_MS1_MA1_ME3", "CB1_DE1_QR1_VO1_QS1_QA1_QO3", "CB1_DE1_MR1_VO1_QS1_QA1_QO3", "CB1_VE1_QR1_QO1_QS1_QA1_QO3", "CB1_VE1_MR1_QO1_QS1_MA1_QO3", "CB1_DE1_MR1_QO1_MS1_QA1_QO3", "CB1_ME1_QR1_VO1_QS1_QA1_QO3", "CB1_VE1_QR1_VO1_MS1_QA1_QO3", "CB1_ME1_QR1_QO1_MS1_QA1_QO3", "CB1_VE1_QR1_DO1_MS1_MA1_QO3", "CB1_VE1_MR1_QO1_MS1_QA1_QO3", "CB1_VE1_MR1_VO1_QS1_MA1_QO3", "CB1_ME1_MR1_VO1_QS1_QA1_QO3", "CB1_ME1_QR1_VO1_MS1_QA1_QO3", "CB1_VE1_MR1_DO1_MS1_QA1_QO3", "CB1_DE1_MR1_DO1_QS1_MA1_QO3", "CB1_VE1_QR1_VO1_QS1_QA1_QO3", "CB1_VE1_QR1_QO1_MS1_MA1_QO3", "CB1_VE1_MR1_DO1_QS1_QA1_QO3", "CB1_DE1_QR1_QO1_QS1_MA1_QO3", "CB1_VE1_QR1_VO1_MS1_MA1_QO3", "CB1_VE1_QR1_VO1_QS1_MA1_QO3", "CB1_DE1_QR1_QO1_MS1_MA1_QO3", "CB1_DE1_MR1_VO1_MS1_QA1_QO3", "CB1_ME1_QR1_DO1_MS1_QA1_QO3", "CB1_ME1_MR1_QO1_MS1_MA1_QO3", "CB1_DE1_MR1_QO1_QS1_MA1_QO3", "CB1_VE1_MR1_VO1_MS1_QA1_QO3", "CB1_VE1_QR1_DO1_QS1_MA1_QO3", "CB1_ME1_QR1_DO1_MS1_MA1_QO3", "CB1_ME1_MR1_DO1_QS1_QA1_QO3", "CB1_ME1_MR1_VO1_QS1_MA1_QO3", "CB1_VE1_QR1_DO1_QS1_QA1_QO3", "QO9", "CB1_DE1_MR1_VO1_MS1_MA1_QO3", "CB1_QO8", "CB1_ME1_QR1_VO1_MS1_MA1_QO3", "CB1_VE1_MR1_VO1_MS1_MA1_QO3", "CB1_ME1_MR1_DO1_MS1_MA1_QO3", "CB1_DE1_QR1_DO1_MS1_QA1_QO3", "CB1_DE1_QR1_VO1_MS1_MA1_QO3", "CB1_ME1_MR1_VO1_MS1_MA1_QO3", "CB1_VE1_MR1_DO1_QS1_MA1_QO3", "CB1_DE1_MR1_DO1_MS1_MA1_QO3", "CB1_ME1_MR1_DO1_MS1_QA1_QO3", "CB1_DE1_MR1_VO1_QS1_MA1_QO3", "CB1_DE1_MR1_DO1_MS1_QA1_QO3", "CB1_DE1_QR1_VO1_QS1_MA1_QO3", "CB1_DE1_QR1_QO1_QS1_QA1_QO3", "CB1_ME1_QR1_DO1_QS1_MA1_QO3", "CB1_VE1_QR1_QO1_MS1_QA1_QO3", "CB1_VE1_MR1_DO1_MS1_MA1_QO3", "CB1_VE1_MR1_QO1_MS1_MA1_QO3", "CB1_ME1_MR1_VO1_MS1_QA1_QO3", "CB1_DE1_MR1_QO1_MS1_MA1_QO3", "CB1_DE1_QR1_DO1_MS1_MA1_QO3"], "last_updated": "2025-02-20"}