{"name": "Composite - ar-vf-yogg-cthun-me", "data": {"Crystallized_Augment_Rune": {"DPS": 2655713}, "Deepfin_Patty": {"DPS": 2651065}, "Marinated_Tenderloins": {"DPS": 2650268}, "Salt_Baked_Seafood": {"DPS": 2650264}, "Fish_and_Chips": {"DPS": 2649755}, "Sweet_and_Spicy_Soup": {"DPS": 2649647}, "Chippy_Tea": {"DPS": 2649544}, "Beledars_Bounty": {"DPS": 2649174}, "Feast_of_the_Divine_Day": {"DPS": 2647622}, "Fiery_Fish_Sticks": {"DPS": 2646458}, "Zesty_Nibblers": {"DPS": 2646258}, "GingerGlazed_Fillet": {"DPS": 2646078}, "Salty_Dog": {"DPS": 2644103}, "Stuffed_Cave_Peppers": {"DPS": 2642092}, "Base": {"DPS": 2635143}}, "ids": {"Crystallized_Augment_Rune": 224572, "Deepfin_Patty": 222718, "Marinated_Tenderloins": 222723, "Salt_Baked_Seafood": 222722, "Fish_and_Chips": 222721, "Sweet_and_Spicy_Soup": 222719, "Chippy_Tea": 222736, "Beledars_Bounty": 222728, "Feast_of_the_Divine_Day": 222732, "Fiery_Fish_Sticks": 222715, "Zesty_Nibblers": 222714, "GingerGlazed_Fillet": 222716, "Salty_Dog": 222717, "Stuffed_Cave_Peppers": 222726}, "simulated_steps": ["DPS"], "sorted_data_keys": ["Crystallized_Augment_Rune", "Deepfin_Patty", "Marinated_Tenderloins", "Salt_Baked_Seafood", "Fish_and_Chips", "Sweet_and_Spicy_Soup", "Chippy_Tea", "Beledars_Bounty", "Feast_of_the_Divine_Day", "Fiery_Fish_Sticks", "Zesty_Nibblers", "GingerGlazed_Fillet", "Salty_Dog", "Stuffed_Cave_Peppers"], "last_updated": "2025-02-20"}