{"name": "Dungeons-Route - ar-vf-yogg-cthun-me", "data": {"Mechagnome": {"DPS": 1930992}, "Maghar_Orc": {"DPS": 1921493}, "Draenei": {"DPS": 1918903}, "Human": {"DPS": 1918508}, "Gnome": {"DPS": 1917622}, "Night_Elf_Haste": {"DPS": 1917239}, "Goblin": {"DPS": 1916978}, "Orc": {"DPS": 1915782}, "Highmountain_Tauren": {"DPS": 1914362}, "Dracthyr": {"DPS": 1914045}, "Kul_Tiran": {"DPS": 1913934}, "Troll": {"DPS": 1913592}, "Nightborne": {"DPS": 1913446}, "Blood_Elf": {"DPS": 1913294}, "Zandalari_Troll_Paku": {"DPS": 1913133}, "Night_Elf_Crit": {"DPS": 1912604}, "Worgen": {"DPS": 1912477}, "Dwarf": {"DPS": 1910408}, "Tauren": {"DPS": 1910246}, "Dark_Iron_Dwarf": {"DPS": 1910191}, "Zandalari_Troll_Kimbul": {"DPS": 1908709}, "Panda_Feast": {"DPS": 1908489}, "Earthen_Emerald": {"DPS": 1902504}, "Zandalari_Troll_Bwonsamdi": {"DPS": 1902405}, "Undead": {"DPS": 1901985}, "Earthen_Onyx": {"DPS": 1901936}, "Earthen_Sapphire": {"DPS": 1900974}, "Earthen_Ruby": {"DPS": 1900765}, "Base": {"DPS": 1899503}, "Void_Elf": {"DPS": 1899468}, "Lightforged_Draenei": {"DPS": 1899380}, "Vulpera": {"DPS": 1899113}}, "ids": {"Mechagnome": 312923, "Maghar_Orc": 274738, "Draenei": 6562, "Human": 20598, "Gnome": 92680, "Night_Elf_Haste": 154748, "Goblin": 69042, "Orc": 33697, "Highmountain_Tauren": 255658, "Dracthyr": 365575, "Kul_Tiran": 291628, "Troll": 26297, "Nightborne": 255665, "Blood_Elf": 154742, "Zandalari_Troll_Paku": 292361, "Night_Elf_Crit": 154748, "Worgen": 68975, "Dwarf": 59224, "Tauren": 154743, "Dark_Iron_Dwarf": 265221, "Zandalari_Troll_Kimbul": 292363, "Panda_Feast": 107072, "Earthen_Emerald": 436341, "Zandalari_Troll_Bwonsamdi": 292360, "Undead": 5227, "Earthen_Onyx": 436341, "Earthen_Sapphire": 436341, "Earthen_Ruby": 436341, "Void_Elf": 255669, "Lightforged_Draenei": 255647, "Vulpera": 312411}, "simulated_steps": ["DPS"], "sorted_data_keys": ["Mechagnome", "Maghar_Orc", "Draenei", "Human", "Gnome", "Night_Elf_Haste", "Goblin", "Orc", "Highmountain_Tauren", "Dracthyr", "Kul_Tiran", "Troll", "Nightborne", "Blood_Elf", "Zandalari_Troll_Paku", "Night_Elf_Crit", "Worgen", "Dwarf", "Tauren", "Dark_Iron_Dwarf", "Zandalari_Troll_Kimbul", "Panda_Feast", "Earthen_Emerald", "Zandalari_Troll_Bwonsamdi", "Undead", "Earthen_Onyx", "Earthen_Sapphire", "Earthen_Ruby", "Void_Elf", "Lightforged_Draenei", "Vulpera"], "last_updated": "2024-12-16"}